{
    "name": "韓玉珍",
    "id": "AN4104749",
    "major": "AN",
    "courses": [
        {
            "course_name": "文學與媒體",
            "course_codes": [
                "B522400"
            ],
            "credit": 2.0,
            "course_type": 2,
            "tag": [],
            "grade": 72,
            "category": " ",
            "year_taken": 112,
            "semester_taken": 1,
            "recognized": false
        },
        {
            "course_name": "傳播文明與媒體",
            "course_codes": [
                "B522300"
            ],
            "credit": 2.0,
            "course_type": 2,
            "tag": [],
            "grade": 74,
            "category": " ",
            "year_taken": 111,
            "semester_taken": 2,
            "recognized": false
        },
        {
            "course_name": "台灣歷史與文化",
            "course_codes": [
                "B514700"
            ],
            "credit": 3.0,
            "course_type": 1,
            "tag": [],
            "grade": 65,
            "category": " ",
            "year_taken": 112,
            "semester_taken": 1,
            "recognized": false
        },
        {
            "course_name": "文學評論與影評寫作",
            "course_codes": [
                "B145300"
            ],
            "credit": 2.0,
            "course_type": 2,
            "tag": [],
            "grade": 80,
            "category": " ",
            "year_taken": 113,
            "semester_taken": 1,
            "recognized": false
        },
        {
            "course_name": "人生哲學",
            "course_codes": [
                "B124500"
            ],
            "credit": 2.0,
            "course_type": 2,
            "tag": [],
            "grade": 85,
            "category": " ",
            "year_taken": 111,
            "semester_taken": 2,
            "recognized": false
        },
        {
            "course_name": "跨領域問題導向-畢業專題",
            "course_codes": [
                "AN40300"
            ],
            "credit": 5.0,
            "course_type": 1,
            "tag": [],
            "grade": 999,
            "category": " ",
            "year_taken": 113,
            "semester_taken": 2,
            "recognized": false
        },
        {
            "course_name": "跨領域問題導向-高階專題",
            "course_codes": [
                "AN30300"
            ],
            "credit": 4.0,
            "course_type": 1,
            "tag": [],
            "grade": 87,
            "category": " ",
            "year_taken": 113,
            "semester_taken": 1,
            "recognized": false
        },
        {
            "course_name": "跨領域問題導向-高階專題",
            "course_codes": [
                "AN30300"
            ],
            "credit": 4.0,
            "course_type": 1,
            "tag": [],
            "grade": 777,
            "category": " ",
            "year_taken": 112,
            "semester_taken": 1,
            "recognized": false
        },
        {
            "course_name": "基礎學術英文",
            "course_codes": [
                "A110500"
            ],
            "credit": 2.0,
            "course_type": 0,
            "tag": [],
            "grade": 53,
            "category": "X",
            "year_taken": 112,
            "semester_taken": 2,
            "recognized": false
        },
        {
            "course_name": "跨文化溝通",
            "course_codes": [
                "A110700"
            ],
            "credit": 2.0,
            "course_type": 0,
            "tag": [],
            "grade": 65,
            "category": "X",
            "year_taken": 111,
            "semester_taken": 2,
            "recognized": false
        },
        {
            "course_name": "聽力與摘記練習",
            "course_codes": [
                "A110800"
            ],
            "credit": 2.0,
            "course_type": 0,
            "tag": [],
            "grade": 90,
            "category": "X",
            "year_taken": 113,
            "semester_taken": 1,
            "recognized": false
        },
        {
            "course_name": "線上補強英文",
            "course_codes": [
                "A130200"
            ],
            "credit": 0.0,
            "course_type": 2,
            "tag": [],
            "grade": 999,
            "category": " ",
            "year_taken": 113,
            "semester_taken": 2,
            "recognized": false
        },
        {
            "course_name": "女子羽球校隊（一）",
            "course_codes": [
                "A217510"
            ],
            "credit": 1.0,
            "course_type": 2,
            "tag": [],
            "grade": 98,
            "category": " ",
            "year_taken": 112,
            "semester_taken": 1,
            "recognized": false
        },
        {
            "course_name": "女子羽球校隊（一）",
            "course_codes": [
                "A217510"
            ],
            "credit": 1.0,
            "course_type": 2,
            "tag": [],
            "grade": 98,
            "category": " ",
            "year_taken": 113,
            "semester_taken": 1,
            "recognized": false
        },
        {
            "course_name": "女子羽球校隊",
            "course_codes": [
                "A221500"
            ],
            "credit": 0.0,
            "course_type": 1,
            "tag": [],
            "grade": 96,
            "category": " ",
            "year_taken": 110,
            "semester_taken": 2,
            "recognized": false
        },
        {
            "course_name": "女子羽球校隊",
            "course_codes": [
                "A221500"
            ],
            "credit": 0.0,
            "course_type": 1,
            "tag": [],
            "grade": 98,
            "category": " ",
            "year_taken": 111,
            "semester_taken": 1,
            "recognized": false
        },
        {
            "course_name": "女子羽球校隊",
            "course_codes": [
                "A221500"
            ],
            "credit": 0.0,
            "course_type": 1,
            "tag": [],
            "grade": 98,
            "category": " ",
            "year_taken": 111,
            "semester_taken": 2,
            "recognized": false
        },
        {
            "course_name": "大學國文-台語電影與文化",
            "course_codes": [
                "A717600"
            ],
            "credit": 2.0,
            "course_type": 0,
            "tag": [],
            "grade": 81,
            "category": "X",
            "year_taken": 110,
            "semester_taken": 2,
            "recognized": false
        },
        {
            "course_name": "財務報告分析",
            "course_codes": [
                "H449300"
            ],
            "credit": 3.0,
            "course_type": 2,
            "tag": [],
            "grade": 777,
            "category": " ",
            "year_taken": 113,
            "semester_taken": 2,
            "recognized": false
        },
        {
            "course_name": "社群與創新",
            "course_codes": [
                "H448400"
            ],
            "credit": 3.0,
            "course_type": 2,
            "tag": [],
            "grade": 88,
            "category": " ",
            "year_taken": 112,
            "semester_taken": 1,
            "recognized": false
        },
        {
            "course_name": "領導學",
            "course_codes": [
                "H445900"
            ],
            "credit": 3.0,
            "course_type": 2,
            "tag": [],
            "grade": 999,
            "category": " ",
            "year_taken": 113,
            "semester_taken": 2,
            "recognized": false
        },
        {
            "course_name": "組織行為",
            "course_codes": [
                "H435700"
            ],
            "credit": 3.0,
            "course_type": 1,
            "tag": [],
            "grade": 89,
            "category": " ",
            "year_taken": 111,
            "semester_taken": 2,
            "recognized": false
        },
        {
            "course_name": "企業智慧策略",
            "course_codes": [
                "H435400"
            ],
            "credit": 3.0,
            "course_type": 2,
            "tag": [],
            "grade": 777,
            "category": " ",
            "year_taken": 113,
            "semester_taken": 1,
            "recognized": false
        },
        {
            "course_name": "大學國文-民間故事與傳說",
            "course_codes": [
                "A718100"
            ],
            "credit": 2.0,
            "course_type": 0,
            "tag": [],
            "grade": 86,
            "category": "X",
            "year_taken": 110,
            "semester_taken": 1,
            "recognized": false
        },
        {
            "course_name": "客家文化導論",
            "course_codes": [
                "A910001"
            ],
            "credit": 2.0,
            "course_type": 1,
            "tag": [],
            "grade": 86,
            "category": "X",
            "year_taken": 110,
            "semester_taken": 2,
            "recognized": false
        },
        {
            "course_name": "臺灣古典文學",
            "course_codes": [
                "A915101"
            ],
            "credit": 2.0,
            "course_type": 0,
            "tag": [],
            "grade": 85,
            "category": "X",
            "year_taken": 113,
            "semester_taken": 1,
            "recognized": false
        },
        {
            "course_name": "踏溯台南",
            "course_codes": [
                "A918701"
            ],
            "credit": 1.0,
            "course_type": 0,
            "tag": [],
            "grade": 95,
            "category": "X",
            "year_taken": 110,
            "semester_taken": 2,
            "recognized": false
        },
        {
            "course_name": "女性文學選讀",
            "course_codes": [
                "A925603"
            ],
            "credit": 2.0,
            "course_type": 1,
            "tag": [],
            "grade": 89,
            "category": "X",
            "year_taken": 112,
            "semester_taken": 1,
            "recognized": false
        },
        {
            "course_name": "日常疼痛控制",
            "course_codes": [
                "A92C400"
            ],
            "credit": 2.0,
            "course_type": 0,
            "tag": [],
            "grade": 62,
            "category": "X",
            "year_taken": 111,
            "semester_taken": 2,
            "recognized": false
        },
        {
            "course_name": "生涯發展",
            "course_codes": [
                "A92H000"
            ],
            "credit": 2.0,
            "course_type": 0,
            "tag": [],
            "grade": 94,
            "category": "X",
            "year_taken": 110,
            "semester_taken": 1,
            "recognized": false
        },
        {
            "course_name": "從電影與繪本談老年",
            "course_codes": [
                "A92T100"
            ],
            "credit": 3.0,
            "course_type": 0,
            "tag": [],
            "grade": 75,
            "category": "X",
            "year_taken": 111,
            "semester_taken": 2,
            "recognized": false
        },
        {
            "course_name": "表演藝術與實作",
            "course_codes": [
                "A93A200"
            ],
            "credit": 2.0,
            "course_type": 0,
            "tag": [],
            "grade": 85,
            "category": "X",
            "year_taken": 113,
            "semester_taken": 1,
            "recognized": false
        },
        {
            "course_name": "心理急救你我他—從心理疾病復元之生命敘事",
            "course_codes": [
                "A93E500"
            ],
            "credit": 2.0,
            "course_type": 0,
            "tag": [],
            "grade": 999,
            "category": "X",
            "year_taken": 113,
            "semester_taken": 2,
            "recognized": false
        },
        {
            "course_name": "食品安全與衛生",
            "course_codes": [
                "A948800"
            ],
            "credit": 2.0,
            "course_type": 0,
            "tag": [],
            "grade": 76,
            "category": "X",
            "year_taken": 111,
            "semester_taken": 2,
            "recognized": false
        },
        {
            "course_name": "心理學",
            "course_codes": [
                "A974500"
            ],
            "credit": 2.0,
            "course_type": 1,
            "tag": [],
            "grade": 77,
            "category": "X",
            "year_taken": 111,
            "semester_taken": 1,
            "recognized": false
        },
        {
            "course_name": "體育（一）",
            "course_codes": [
                "A215500"
            ],
            "credit": 0.0,
            "course_type": 0,
            "tag": [],
            "grade": 95,
            "category": " ",
            "year_taken": 110,
            "semester_taken": 1,
            "recognized": false
        },
        {
            "course_name": "操行",
            "course_codes": [
                "AN09980"
            ],
            "credit": 0.0,
            "course_type": 1,
            "tag": [],
            "grade": 85,
            "category": " ",
            "year_taken": 110,
            "semester_taken": 1,
            "recognized": false
        },
        {
            "course_name": "操行",
            "course_codes": [
                "AN09980"
            ],
            "credit": 0.0,
            "course_type": 1,
            "tag": [],
            "grade": 88,
            "category": " ",
            "year_taken": 111,
            "semester_taken": 1,
            "recognized": false
        },
        {
            "course_name": "操行",
            "course_codes": [
                "AN09980"
            ],
            "credit": 0.0,
            "course_type": 1,
            "tag": [],
            "grade": 88,
            "category": " ",
            "year_taken": 113,
            "semester_taken": 1,
            "recognized": false
        },
        {
            "course_name": "操行",
            "course_codes": [
                "AN09980"
            ],
            "credit": 0.0,
            "course_type": 1,
            "tag": [],
            "grade": 86,
            "category": " ",
            "year_taken": 110,
            "semester_taken": 2,
            "recognized": false
        },
        {
            "course_name": "操行",
            "course_codes": [
                "AN09980"
            ],
            "credit": 0.0,
            "course_type": 1,
            "tag": [],
            "grade": 88,
            "category": " ",
            "year_taken": 112,
            "semester_taken": 1,
            "recognized": false
        },
        {
            "course_name": "操行",
            "course_codes": [
                "AN09980"
            ],
            "credit": 0.0,
            "course_type": 1,
            "tag": [],
            "grade": 87,
            "category": " ",
            "year_taken": 111,
            "semester_taken": 2,
            "recognized": false
        },
        {
            "course_name": "跨領域問題導向-進階專題",
            "course_codes": [
                "AN20900"
            ],
            "credit": 4.0,
            "course_type": 1,
            "tag": [],
            "grade": 88,
            "category": " ",
            "year_taken": 112,
            "semester_taken": 2,
            "recognized": false
        },
        {
            "course_name": "服務學習（一）",
            "course_codes": [
                "AN10110"
            ],
            "credit": 0.0,
            "course_type": 1,
            "tag": [],
            "grade": 88,
            "category": " ",
            "year_taken": 110,
            "semester_taken": 1,
            "recognized": false
        },
        {
            "course_name": "服務學習（二）",
            "course_codes": [
                "AN10120"
            ],
            "credit": 0.0,
            "course_type": 1,
            "tag": [],
            "grade": 91,
            "category": " ",
            "year_taken": 110,
            "semester_taken": 2,
            "recognized": false
        },
        {
            "course_name": "跨領域問題導向-初階專題",
            "course_codes": [
                "AN16000"
            ],
            "credit": 5.0,
            "course_type": 1,
            "tag": [],
            "grade": 94,
            "category": " ",
            "year_taken": 110,
            "semester_taken": 1,
            "recognized": false
        },
        {
            "course_name": "仿生學",
            "course_codes": [
                "AN16500"
            ],
            "credit": 2.0,
            "course_type": 2,
            "tag": [],
            "grade": 89,
            "category": " ",
            "year_taken": 110,
            "semester_taken": 1,
            "recognized": false
        },
        {
            "course_name": "跨領域跨國品牌策展實務",
            "course_codes": [
                "AN18400"
            ],
            "credit": 2.0,
            "course_type": 2,
            "tag": [],
            "grade": 88,
            "category": " ",
            "year_taken": 110,
            "semester_taken": 1,
            "recognized": false
        },
        {
            "course_name": "肌力與體能訓練之科技應用與實務",
            "course_codes": [
                "AN1C400"
            ],
            "credit": 2.0,
            "course_type": 2,
            "tag": [],
            "grade": 97,
            "category": " ",
            "year_taken": 110,
            "semester_taken": 1,
            "recognized": false
        },
        {
            "course_name": "從古代到近代：中國思想與人文世界",
            "course_codes": [
                "AN1D200"
            ],
            "credit": 2.0,
            "course_type": 2,
            "tag": [],
            "grade": 93,
            "category": " ",
            "year_taken": 112,
            "semester_taken": 2,
            "recognized": false
        },
        {
            "course_name": "創業實踐與創意思考",
            "course_codes": [
                "AN20300"
            ],
            "credit": 3.0,
            "course_type": 2,
            "tag": [],
            "grade": 88,
            "category": " ",
            "year_taken": 110,
            "semester_taken": 1,
            "recognized": false
        },
        {
            "course_name": "操行",
            "course_codes": [
                "AN09980"
            ],
            "credit": 0.0,
            "course_type": 1,
            "tag": [],
            "grade": 89,
            "category": " ",
            "year_taken": 112,
            "semester_taken": 2,
            "recognized": false
        },
        {
            "course_name": "管理學",
            "course_codes": [
                "H430700"
            ],
            "credit": 3.0,
            "course_type": 1,
            "tag": [],
            "grade": 77,
            "category": " ",
            "year_taken": 111,
            "semester_taken": 1,
            "recognized": false
        },
        {
            "course_name": "商事法",
            "course_codes": [
                "H430301"
            ],
            "credit": 3.0,
            "course_type": 2,
            "tag": [],
            "grade": 80,
            "category": " ",
            "year_taken": 110,
            "semester_taken": 2,
            "recognized": false
        },
        {
            "course_name": "氣候變遷與永續投資",
            "course_codes": [
                "H423800"
            ],
            "credit": 1.0,
            "course_type": 2,
            "tag": [],
            "grade": 89,
            "category": " ",
            "year_taken": 113,
            "semester_taken": 1,
            "recognized": false
        },
        {
            "course_name": "初級績效管理應用",
            "course_codes": [
                "H423100"
            ],
            "credit": 3.0,
            "course_type": 2,
            "tag": [],
            "grade": 90,
            "category": " ",
            "year_taken": 111,
            "semester_taken": 1,
            "recognized": false
        },
        {
            "course_name": "管理決策分析",
            "course_codes": [
                "H421700"
            ],
            "credit": 3.0,
            "course_type": 2,
            "tag": [],
            "grade": 73,
            "category": " ",
            "year_taken": 113,
            "semester_taken": 1,
            "recognized": false
        },
        {
            "course_name": "統計學（一）",
            "course_codes": [
                "H420710"
            ],
            "credit": 3.0,
            "course_type": 1,
            "tag": [],
            "grade": 45,
            "category": " ",
            "year_taken": 112,
            "semester_taken": 1,
            "recognized": false
        },
        {
            "course_name": "經濟學（二）",
            "course_codes": [
                "H415520"
            ],
            "credit": 3.0,
            "course_type": 1,
            "tag": [],
            "grade": 84,
            "category": " ",
            "year_taken": 110,
            "semester_taken": 2,
            "recognized": false
        },
        {
            "course_name": "經濟學（一）",
            "course_codes": [
                "H415510"
            ],
            "credit": 3.0,
            "course_type": 1,
            "tag": [],
            "grade": 67,
            "category": " ",
            "year_taken": 111,
            "semester_taken": 1,
            "recognized": false
        },
        {
            "course_name": "社群媒體行銷",
            "course_codes": [
                "H411800"
            ],
            "credit": 3.0,
            "course_type": 2,
            "tag": [],
            "grade": 87,
            "category": " ",
            "year_taken": 112,
            "semester_taken": 2,
            "recognized": false
        },
        {
            "course_name": "微積分（二）",
            "course_codes": [
                "D511221"
            ],
            "credit": 3.0,
            "course_type": 1,
            "tag": [],
            "grade": 40,
            "category": " ",
            "year_taken": 111,
            "semester_taken": 2,
            "recognized": false
        },
        {
            "course_name": "微積分（一）",
            "course_codes": [
                "D511211"
            ],
            "credit": 3.0,
            "course_type": 1,
            "tag": [],
            "grade": 55,
            "category": " ",
            "year_taken": 111,
            "semester_taken": 1,
            "recognized": false
        },
        {
            "course_name": "會計學（二）",
            "course_codes": [
                "H230420"
            ],
            "credit": 3.0,
            "course_type": 1,
            "tag": [],
            "grade": 81,
            "category": " ",
            "year_taken": 111,
            "semester_taken": 2,
            "recognized": false
        },
        {
            "course_name": "會計學（一）",
            "course_codes": [
                "H230210"
            ],
            "credit": 3.0,
            "course_type": 1,
            "tag": [],
            "grade": 84,
            "category": " ",
            "year_taken": 111,
            "semester_taken": 1,
            "recognized": false
        },
        {
            "course_name": "統計學（二）",
            "course_codes": [
                "H120320"
            ],
            "credit": 3.0,
            "course_type": 1,
            "tag": [],
            "grade": 999,
            "category": " ",
            "year_taken": 113,
            "semester_taken": 2,
            "recognized": false
        },
        {
            "course_name": "統計學（二）",
            "course_codes": [
                "H120320"
            ],
            "credit": 3.0,
            "course_type": 1,
            "tag": [],
            "grade": 46,
            "category": " ",
            "year_taken": 112,
            "semester_taken": 2,
            "recognized": false
        },
        {
            "course_name": "統計學（一）",
            "course_codes": [
                "H120310"
            ],
            "credit": 3.0,
            "course_type": 1,
            "tag": [],
            "grade": 40,
            "category": " ",
            "year_taken": 113,
            "semester_taken": 1,
            "recognized": false
        },
        {
            "course_name": "微積分（二）",
            "course_codes": [
                "H115621"
            ],
            "credit": 3.0,
            "course_type": 2,
            "tag": [],
            "grade": 999,
            "category": " ",
            "year_taken": 113,
            "semester_taken": 2,
            "recognized": false
        },
        {
            "course_name": "微積分（二）",
            "course_codes": [
                "H115621"
            ],
            "credit": 3.0,
            "course_type": 2,
            "tag": [],
            "grade": 46,
            "category": " ",
            "year_taken": 112,
            "semester_taken": 2,
            "recognized": false
        },
        {
            "course_name": "微積分（一）",
            "course_codes": [
                "H115611"
            ],
            "credit": 3.0,
            "course_type": 1,
            "tag": [],
            "grade": 60,
            "category": " ",
            "year_taken": 112,
            "semester_taken": 1,
            "recognized": false
        },
        {
            "course_name": "微積分（一）",
            "course_codes": [
                "E515611"
            ],
            "credit": 3.0,
            "course_type": 1,
            "tag": [],
            "grade": 777,
            "category": " ",
            "year_taken": 110,
            "semester_taken": 1,
            "recognized": false
        },
        {
            "course_name": "材料科學導論",
            "course_codes": [
                "E511200"
            ],
            "credit": 3.0,
            "course_type": 1,
            "tag": [],
            "grade": 777,
            "category": " ",
            "year_taken": 110,
            "semester_taken": 1,
            "recognized": false
        },
        {
            "course_name": "中華民國憲法與政府",
            "course_codes": [
                "D410211"
            ],
            "credit": 3.0,
            "course_type": 1,
            "tag": [],
            "grade": 70,
            "category": " ",
            "year_taken": 110,
            "semester_taken": 2,
            "recognized": false
        },
        {
            "course_name": "生物資料分析：Python語言",
            "course_codes": [
                "C631600"
            ],
            "credit": 2.0,
            "course_type": 2,
            "tag": [],
            "grade": 65,
            "category": " ",
            "year_taken": 110,
            "semester_taken": 2,
            "recognized": false
        },
        {
            "course_name": "生物科技概論",
            "course_codes": [
                "C611800"
            ],
            "credit": 2.0,
            "course_type": 1,
            "tag": [],
            "grade": 51,
            "category": " ",
            "year_taken": 110,
            "semester_taken": 2,
            "recognized": false
        },
        {
            "course_name": "媒體社會學",
            "course_codes": [
                "B543400"
            ],
            "credit": 3.0,
            "course_type": 2,
            "tag": [],
            "grade": 88,
            "category": " ",
            "year_taken": 112,
            "semester_taken": 2,
            "recognized": false
        },
        {
            "course_name": "新聞台語",
            "course_codes": [
                "B542700"
            ],
            "credit": 2.0,
            "course_type": 2,
            "tag": [],
            "grade": 89,
            "category": " ",
            "year_taken": 111,
            "semester_taken": 1,
            "recognized": false
        },
        {
            "course_name": "台語閱讀與寫作",
            "course_codes": [
                "B525400"
            ],
            "credit": 2.0,
            "course_type": 2,
            "tag": [],
            "grade": 999,
            "category": " ",
            "year_taken": 113,
            "semester_taken": 2,
            "recognized": false
        },
        {
            "course_name": "觀光台語",
            "course_codes": [
                "B524600"
            ],
            "credit": 2.0,
            "course_type": 2,
            "tag": [],
            "grade": 88,
            "category": " ",
            "year_taken": 110,
            "semester_taken": 2,
            "recognized": false
        }
    ],
    "admission_year": 110
}